epyt_flow/VERSION
epyt_flow/__init__.py
epyt_flow/serialization.py
epyt_flow/topology.py
epyt_flow/utils.py
epyt_flow/data/__init__.py
epyt_flow/data/networks.py
epyt_flow/data/benchmarks/__init__.py
epyt_flow/data/benchmarks/batadal.py
epyt_flow/data/benchmarks/batadal_data.py
epyt_flow/data/benchmarks/battledim.py
epyt_flow/data/benchmarks/battledim_data.py
epyt_flow/data/benchmarks/gecco_water_quality.py
epyt_flow/data/benchmarks/leakdb.py
epyt_flow/data/benchmarks/leakdb_data.py
epyt_flow/data/benchmarks/water_usage.py
epyt_flow/gym/__init__.py
epyt_flow/gym/scenario_control_env.py
epyt_flow/rest_api/__init__.py
epyt_flow/rest_api/base_handler.py
epyt_flow/rest_api/res_manager.py
epyt_flow/rest_api/server.py
epyt_flow/rest_api/scada_data/__init__.py
epyt_flow/rest_api/scada_data/data_handlers.py
epyt_flow/rest_api/scada_data/export_handlers.py
epyt_flow/rest_api/scada_data/handlers.py
epyt_flow/rest_api/scenario/__init__.py
epyt_flow/rest_api/scenario/control_handlers.py
epyt_flow/rest_api/scenario/event_handlers.py
epyt_flow/rest_api/scenario/handlers.py
epyt_flow/rest_api/scenario/simulation_handlers.py
epyt_flow/rest_api/scenario/uncertainty_handlers.py
epyt_flow/simulation/__init__.py
epyt_flow/simulation/parallel_simulation.py
epyt_flow/simulation/scenario_config.py
epyt_flow/simulation/scenario_simulator.py
epyt_flow/simulation/sensor_config.py
epyt_flow/simulation/events/__init__.py
epyt_flow/simulation/events/actuator_events.py
epyt_flow/simulation/events/event.py
epyt_flow/simulation/events/leakages.py
epyt_flow/simulation/events/quality_events.py
epyt_flow/simulation/events/sensor_faults.py
epyt_flow/simulation/events/sensor_reading_attack.py
epyt_flow/simulation/events/sensor_reading_event.py
epyt_flow/simulation/events/system_event.py
epyt_flow/simulation/scada/__init__.py
epyt_flow/simulation/scada/complex_control.py
epyt_flow/simulation/scada/custom_control.py
epyt_flow/simulation/scada/scada_data.py
epyt_flow/simulation/scada/scada_data_export.py
epyt_flow-0.15.0.dist-info/licenses/LICENSE
epyt_flow-0.15.0.dist-info/METADATA
epyt_flow-0.15.0.dist-info/WHEEL
epyt_flow-0.15.0.dist-info/top_level.txt
epyt_flow-0.15.0.dist-info/RECORD
