Metadata-Version: 2.4
Name: epyt-flow
Version: 0.15.0
Summary: EPyT-Flow -- EPANET Python Toolkit - Flow
Author-email: André Artelt <aartelt@techfak.uni-bielefeld.de>, "Marios S. Kyriakou" <kiriakou.marios@ucy.ac.cy>, "Stelios G. Vrachimis" <vrachimis.stelios@ucy.ac.cy>
License-Expression: MIT
Project-URL: Homepage, https://github.com/WaterFutures/EPyT-Flow
Project-URL: Documentation, https://epyt-flow.readthedocs.io/en/stable/
Project-URL: Repository, https://github.com/WaterFutures/EPyT-Flow.git
Project-URL: Issues, https://github.com/WaterFutures/EPyT-Flow/issues
Keywords: epanet,water,networks,hydraulics,quality,simulations
Classifier: Development Status :: 4 - Beta
Classifier: Intended Audience :: Science/Research
Classifier: Programming Language :: Python :: 3
Classifier: Programming Language :: Python :: 3.9
Classifier: Programming Language :: Python :: 3.10
Classifier: Programming Language :: Python :: 3.11
Classifier: Programming Language :: Python :: 3.12
Classifier: Programming Language :: Python :: 3.13
Classifier: Programming Language :: Python :: 3.14
Requires-Python: >=3.9
License-File: LICENSE
Requires-Dist: epanet-plus>=0.1.2
Requires-Dist: requests>=2.31.0
Requires-Dist: scipy>=1.11.4
Requires-Dist: u-msgpack-python>=2.8.0
Requires-Dist: networkx>=3.2.1
Requires-Dist: scikit-learn>=1.4.0
Requires-Dist: tqdm>=4.66.2
Requires-Dist: openpyxl>=3.1.2
Requires-Dist: falcon>=3.1.3
Requires-Dist: multiprocess>=0.70.16
Requires-Dist: geopandas>=0.14.4
Requires-Dist: svgpath2mpl>=1.0.0
Requires-Dist: Deprecated>=1.2.14
Requires-Dist: psutil
Dynamic: license-file
